Metadata-Version: 2.1
Name: memoraith
Version: 0.4.0
Summary: Advanced lightweight model profiler for deep learning frameworks
Home-page: https://github.com/mehdi342/Memoraith
Author: Mehdi El Jouhfi
Author-email: midojouhfi@gmail.com
Project-URL: Bug Reports, https://github.com/mehdi342/Memoraith/issues
Project-URL: Source, https://github.com/mehdi342/Memoraith/
Classifier: Development Status :: 4 - Beta
Classifier: Intended Audience :: Developers
Classifier: Intended Audience :: Science/Research
Classifier: License :: OSI Approved :: MIT License
Classifier: Programming Language :: Python :: 3
Classifier: Programming Language :: Python :: 3.7
Classifier: Programming Language :: Python :: 3.8
Classifier: Programming Language :: Python :: 3.9
Classifier: Topic :: Scientific/Engineering :: Artificial Intelligence
Requires-Python: >=3.7
License-File: LICENSE
Requires-Dist: torch>=1.7.0
Requires-Dist: tensorflow>=2.4.0
Requires-Dist: matplotlib>=3.3.0
Requires-Dist: seaborn>=0.11.0
Requires-Dist: plotly>=4.14.0
Requires-Dist: pandas>=1.2.0
Requires-Dist: jinja2>=2.11.0
Requires-Dist: pdfkit>=0.6.0
Requires-Dist: psutil>=5.8.0
Requires-Dist: pynvml>=8.0.0
Requires-Dist: colorama>=0.4.4
Requires-Dist: tqdm>=4.60.0
Requires-Dist: aiofiles>=0.6.0
Requires-Dist: asyncio>=3.4.3
Requires-Dist: networkx>=2.5
Requires-Dist: python-dotenv>=0.19.0
Requires-Dist: pyyaml>=5.4.0
Provides-Extra: full
Requires-Dist: torch>=1.7.0; extra == "full"
Requires-Dist: tensorflow>=2.4.0; extra == "full"
Requires-Dist: tensorboard>=2.4.0; extra == "full"
Requires-Dist: optuna>=2.3.0; extra == "full"
Requires-Dist: ray>=1.2.0; extra == "full"
Provides-Extra: dev
Requires-Dist: pytest>=6.2.0; extra == "dev"
Requires-Dist: pytest-asyncio>=0.14.0; extra == "dev"
Requires-Dist: black>=20.8b1; extra == "dev"
Requires-Dist: isort>=5.7.0; extra == "dev"
Requires-Dist: flake8>=3.8.0; extra == "dev"
Requires-Dist: mypy>=0.800; extra == "dev"
Requires-Dist: tox>=3.20.0; extra == "dev"
Requires-Dist: sphinx>=3.4.3; extra == "dev"
Requires-Dist: sphinx-rtd-theme>=0.5.1; extra == "dev"
